aaaazzzz_portal_gun/__init__.py
aaaazzzz_portal_gun/__main__.py
aaaazzzz_portal_gun/main.py
aaaazzzz_portal_gun-0.1.0.dist-info/entry_points.txt
aaaazzzz_portal_gun-0.1.0.dist-info/METADATA
aaaazzzz_portal_gun-0.1.0.dist-info/WHEEL
aaaazzzz_portal_gun-0.1.0.dist-info/RECORD
